{"$schema":"https://json-schema.org/draft/2020-12/schema","$defs":{"indices.analyze__TextToAnalyze":{"oneOf":[{"type":"string"},{"type":"array","items":{"type":"string"}}]},"indices.analyze__AnalyzeDetail":{"type":"object","properties":{"analyzer":{"$ref":"./indices.analyze.json#/$defs/indices.analyze__AnalyzerDetail"},"charfilters":{"type":"array","items":{"$ref":"./indices.analyze.json#/$defs/indices.analyze__CharFilterDetail"}},"custom_analyzer":{"type":"boolean"},"tokenfilters":{"type":"array","items":{"$ref":"./indices.analyze.json#/$defs/indices.analyze__TokenDetail"}},"tokenizer":{"$ref":"./indices.analyze.json#/$defs/indices.analyze__TokenDetail"}},"required":["custom_analyzer"]},"indices.analyze__AnalyzerDetail":{"type":"object","properties":{"name":{"type":"string"},"tokens":{"type":"array","items":{"$ref":"./indices.analyze.json#/$defs/indices.analyze__ExplainAnalyzeToken"}}},"required":["name","tokens"]},"indices.analyze__ExplainAnalyzeToken":{"type":"object","additionalProperties":{}},"indices.analyze__CharFilterDetail":{"type":"object","properties":{"filtered_text":{"type":"array","items":{"type":"string"}},"name":{"type":"string"}},"required":["filtered_text","name"]},"indices.analyze__TokenDetail":{"type":"object","properties":{"name":{"type":"string"},"tokens":{"type":"array","items":{"$ref":"./indices.analyze.json#/$defs/indices.analyze__ExplainAnalyzeToken"}}},"required":["name","tokens"]},"indices.analyze__AnalyzeToken":{"type":"object","properties":{"end_offset":{"type":"number"},"position":{"type":"number"},"positionLength":{"type":"number"},"start_offset":{"type":"number"},"token":{"type":"string"},"type":{"type":"string"}},"required":["end_offset","position","start_offset","token","type"]}}}