{"$schema":"https://json-schema.org/draft/2020-12/schema","title":"security.delete_service_token","type":"object","properties":{"namespace":{"type":"string","description":"The namespace, which is a top-level grouping of service accounts."},"service":{"type":"string","description":"The service name."},"name":{"type":"string","description":"The name of the service account token."},"refresh":{"$ref":"./_types.json#/$defs/_types__Refresh","description":"If `true` (the default) then refresh the affected shards to make this operation visible to search, if `wait_for` then wait for a refresh to make this operation visible to search, if `false` then do nothing with refreshes."}},"required":["namespace","service","name"],"description":"Delete service account tokens.\n\nDelete service account tokens for a service in a specified namespace.\n\nIMPORTANT: On Serverless, non-operator users can delete tokens for only `elastic/fleet-server` and `elastic/fleet-server-remote`.\nDeleting tokens for any other service account requires operator privileges."}